get_read_percid/__init__.py
get_read_percid/__main__.py
get_read_percid/_version.py
get_read_percid/defaults.py
get_read_percid/extract.py
get_read_percid/lib.py
get_read_percid/utils.py
get_read_percid-0.0.3.dist-info/LICENSE
get_read_percid-0.0.3.dist-info/METADATA
get_read_percid-0.0.3.dist-info/WHEEL
get_read_percid-0.0.3.dist-info/entry_points.txt
get_read_percid-0.0.3.dist-info/top_level.txt
get_read_percid-0.0.3.dist-info/RECORD
