Metadata-Version: 2.1
Name: get-read-percid
Version: 0.0.3
Summary: A simple tool to extract references from BAM files and get read statistics
Home-page: https://github.com/genomewalker/get-read-percid
Author: Antonio Fernandez-Guerra
Author-email: antonio@metagenomics.eu
License: MIT
Keywords: get-read-percid
Platform: UNKNOWN
Classifier: Programming Language :: Python :: 3.8
Classifier: Programming Language :: Python :: 3.9
License-File: LICENSE
Requires-Dist: pandas (>=1.4.2)
Requires-Dist: tqdm (>=4.64.1)
Requires-Dist: pysam (>=0.17.0)
Requires-Dist: numpy (>=1.21.2)
Requires-Dist: biopython (>=1.79)
